stacks/__init__.py
stacks/data/__init__.py
stacks/data/behave/__init__.py
stacks/data/behave/fixtures.py
stacks/data/behave/shared_steps.py
stacks/data/cli/__init__.py
stacks/data/cli/datastacks_cli.py
stacks/data/generate/__init__.py
stacks/data/generate/data_workloads.py
stacks/data/generate/template_config.py
stacks/data/generate/templates/ingest/ingest_template/README.md.jinja
stacks/data/generate/templates/ingest/ingest_template/__init__.py.jinja
stacks/data/generate/templates/ingest/ingest_template/config/ingest_sources/ingest_config.json.jinja
stacks/data/generate/templates/ingest/ingest_template/config/schema/ingest_config_schema.json.jinja
stacks/data/generate/templates/ingest/ingest_template/data_factory/adf_datasets.tf.jinja
stacks/data/generate/templates/ingest/ingest_template/data_factory/adf_linked_services.tf.jinja
stacks/data/generate/templates/ingest/ingest_template/data_factory/adf_pipelines.tf.jinja
stacks/data/generate/templates/ingest/ingest_template/data_factory/adf_triggers.tf.jinja
stacks/data/generate/templates/ingest/ingest_template/data_factory/constraints.tf.jinja
stacks/data/generate/templates/ingest/ingest_template/data_factory/data.tf.jinja
stacks/data/generate/templates/ingest/ingest_template/data_factory/pipelines/arm_template.json.jinja
stacks/data/generate/templates/ingest/ingest_template/data_factory/provider.tf.jinja
stacks/data/generate/templates/ingest/ingest_template/data_factory/vars.tf.jinja
stacks/data/generate/templates/ingest/ingest_template/de-ingest-ado-pipeline.yml.jinja
stacks/data/generate/templates/ingest/ingest_template/tests/__init__.py.jinja
stacks/data/generate/templates/ingest/ingest_template/tests/end_to_end/__init__.py.jinja
stacks/data/generate/templates/ingest/ingest_template/tests/end_to_end/features/__init__.py.jinja
stacks/data/generate/templates/ingest/ingest_template/tests/end_to_end/features/azure_data_ingest.feature.jinja
stacks_data-2.1.4.dist-info/LICENSE
stacks_data-2.1.4.dist-info/METADATA
stacks_data-2.1.4.dist-info/WHEEL
stacks_data-2.1.4.dist-info/entry_points.txt
stacks_data-2.1.4.dist-info/RECORD
