Metadata-Version: 2.1
Name: stacks-data
Version: 2.1.4
Summary: A suite of utilities to support data engineering workloads within an Ensono Stacks data platform.
Home-page: https://github.com/Ensono/stacks-data
Author: Ensono Stacks
Author-email: stacks@ensono.com
Requires-Python: >=3.9,<4.0
Classifier: Programming Language :: Python :: 3
Classifier: Programming Language :: Python :: 3.9
Classifier: Programming Language :: Python :: 3.10
Classifier: Programming Language :: Python :: 3.11
Classifier: Programming Language :: Python :: 3.12
Provides-Extra: behave
Provides-Extra: cli
Provides-Extra: data-quality
Requires-Dist: azure-core (==1.38.0)
Requires-Dist: azure-identity (==1.16.1)
Requires-Dist: azure-mgmt-datafactory (>=3.1.0,<4.0.0)
Requires-Dist: azure-storage-file-datalake (>=12.16.0,<13.0.0)
Requires-Dist: behave (>=1.2.6,<2.0.0) ; extra == "behave"
Requires-Dist: click (>=8.1.7,<9.0.0) ; extra == "cli"
Requires-Dist: click-loglevel (>=0.4.0.post1,<0.5.0) ; extra == "cli"
Requires-Dist: colorlog (>=6.8.2,<7.0.0)
Requires-Dist: delta-spark (>=2.4.0,<4.0.0)
Requires-Dist: great-expectations (>=0.17.23,<0.18.0) ; extra == "data-quality"
Requires-Dist: jinja2 (>=3.1.4,<4.0.0) ; extra == "cli"
Requires-Dist: jsonschema (>=4.23.0,<5.0.0)
Requires-Dist: polling2 (>=0.5.0,<0.6.0) ; extra == "behave"
Requires-Dist: pydantic (>=1.10.18,<2.0.0)
Requires-Dist: pyspark (>=3.4.3,<4.0.0)
Requires-Dist: pyyaml (>=6.0.2,<7.0.0)
